<?xml version="1.0"?>
<dlgData xmlns:xsd="http://www.w3.org/2001/XMLSchema" xmlns:xsi="http://www.w3.org/2001/XMLSchema-instance">
  <header>
    <conditions />
    <links />
    <dlg_name>Paul_Bit</dlg_name>
    <def_link>1142</def_link>
  </header>
  <parts>
    <dlgPart>
      <lines>
        <dlgLine>
          <owner_ID>0</owner_ID>
          <text>Quelque chose que tu dois savoir... J'ai été mordu. Je préférerais que ça reste entre toi et moi. Ça ne rendra service à personne d'entendre qu'une autre personne a été infectée.</text>
          <defAppearChecks>
            <boolean>false</boolean>
            <boolean>false</boolean>
            <boolean>false</boolean>
            <boolean>false</boolean>
            <boolean>false</boolean>
            <boolean>false</boolean>
            <boolean>false</boolean>
            <boolean>false</boolean>
          </defAppearChecks>
          <onAppearChecks />
          <onLoadScripts>
            <string>ds.Paul_Bit = 1;</string>
          </onLoadScripts>
        </dlgLine>
      </lines>
      <answers>
        <!-- clone pour genre -->
        <dlgAnsw>
          <text>Je suis vraiment désolée de l'apprendre, Paul.</text>
          <def_link>1143</def_link>
          <auto_answer>false</auto_answer>
          <checkOnAppear>isPcFemale()</checkOnAppear>
          <checksOnClick />
          <linksOnClick />
          <scriptsOnClick />
        </dlgAnsw>
        <dlgAnsw>
          <text>Je suis vraiment désolé de l'apprendre, Paul.</text>
          <def_link>1143</def_link>
          <auto_answer>false</auto_answer>
          <checkOnAppear>isPcMale()</checkOnAppear>
          <checksOnClick />
          <linksOnClick />
          <scriptsOnClick />
        </dlgAnsw>
        <dlgAnsw>
          <text>Bon sang... Pas un autre.</text>
          <def_link>1144</def_link>
          <auto_answer>false</auto_answer>
          <checkOnAppear />
          <checksOnClick />
          <linksOnClick />
          <scriptsOnClick />
        </dlgAnsw>
      </answers>
      <UID>1142</UID>
    </dlgPart>
    <dlgPart>
      <lines>
        <dlgLine>
          <owner_ID>0</owner_ID>
          <text>Oui... Je veux juste que tu saches que tant que je le pourrai, je ferai tout ce qu'il faut pour que cet endroit reste uni. C'est une promesse.</text>
          <defAppearChecks>
            <boolean>false</boolean>
            <boolean>false</boolean>
            <boolean>false</boolean>
            <boolean>false</boolean>
            <boolean>false</boolean>
            <boolean>false</boolean>
            <boolean>false</boolean>
            <boolean>false</boolean>
          </defAppearChecks>
          <onAppearChecks />
          <onLoadScripts />
        </dlgLine>
      </lines>
      <answers>
        <dlgAnsw>
          <text>&lt;Paul s'en va.&gt;</text>
          <def_link>-1</def_link>
          <auto_answer>false</auto_answer>
          <checkOnAppear />
          <checksOnClick />
          <linksOnClick />
          <scriptsOnClick>
            <string>dlgEndFadeFullFast();</string>
          </scriptsOnClick>
        </dlgAnsw>
      </answers>
      <UID>1143</UID>
    </dlgPart>
    <dlgPart>
      <lines>
        <dlgLine>
          <owner_ID>0</owner_ID>
          <text>Hé, ne vous en faites pas, c'est moi qui devrais m'inquiéter. Juste... ne t'inquiète pas pour ça.</text>
          <defAppearChecks>
            <boolean>false</boolean>
            <boolean>false</boolean>
            <boolean>false</boolean>
            <boolean>false</boolean>
            <boolean>false</boolean>
            <boolean>false</boolean>
            <boolean>false</boolean>
            <boolean>false</boolean>
          </defAppearChecks>
          <onAppearChecks />
          <onLoadScripts />
        </dlgLine>
      </lines>
      <answers>
        <dlgAnsw>
          <text>&lt;Paul s'en va.&gt;</text>
          <def_link>-1</def_link>
          <auto_answer>false</auto_answer>
          <checkOnAppear />
          <checksOnClick />
          <linksOnClick />
          <scriptsOnClick>
            <string>dlgEndFadeFullFast();</string>
          </scriptsOnClick>
        </dlgAnsw>
      </answers>
      <UID>1144</UID>
    </dlgPart>
  </parts>
  <participants>
    <dlgParticipant>
      <UID>0</UID>
      <charID>1006</charID>
      <name>Paul</name>
      <role>Speaker</role>
      <req>AliveShelterChar</req>
      <color>Black</color>
    </dlgParticipant>
  </participants>
</dlgData>